{
    "version": "0.107.1",
    "description": "Privacy protection center for you and your devices",
    "homepage": "https://github.com/AdguardTeam/AdGuardHome",
    "license": "GPL-3.0",
    "url": "https://github.com/AdguardTeam/AdGuardHome/releases/download/v0.107.1/AdGuardHome_windows_amd64.zip",
    "extract_dir": "AdGuardHome",
    "hash": "9e0ac809fb650503b387e289f2e67cc447cc7d541d907fb727ac0a8e923c4c6c",
    "bin": "AdGuardHome.exe",
    "checkver": {
        "github": "https://github.com/AdguardTeam/AdGuardHome"
    },
    "autoupdate": {
        "url": "https://github.com/AdguardTeam/AdGuardHome/releases/download/v$version/AdGuardHome_windows_amd64.zip",
        "extract_dir": "AdGuardHome"
    },
    "persist": [
        "data",
        "AdGuardHome.yaml"
    ]
}
