{
    "version": "1.8.7",
    "description": "游戏加速器",
    "homepage": "https://netch.org/",
    "license": "GPL-3.0-only",
    "url": "https://github.com/NetchX/Netch/releases/download/1.8.7/Netch.7z",
    "hash": "ba2a70ece4cf63f029beff265c358099f08101bd587cbed286c09039f097bbcb",
    "shortcuts": [
        [
            "Netch.exe",
            "Netch"
        ]
    ],
    "checkver": {
        "github": "https://github.com/NetchX/Netch"
    },
    "autoupdate": {
        "url": "https://github.com/NetchX/Netch/releases/download/$version/Netch.7z",
        "hash": {
            "url": "https://github.com/NetchX/Netch/releases/latest"
        }
    },
    "persist": [
        "data",
        "mode"
    ]
}
